DataQualityProcessor/__init__.py
DataQualityProcessor/config.py
DataQualityProcessor/configs_all.yml
DataQualityProcessor/data_qulaity_processor.py
DataQualityTransformation-0.0.1.dist-info/METADATA
DataQualityTransformation-0.0.1.dist-info/WHEEL
DataQualityTransformation-0.0.1.dist-info/top_level.txt
DataQualityTransformation-0.0.1.dist-info/RECORD
