Metadata-Version: 2.1
Name: DataQualityTransformation
Version: 0.0.1
Summary: Cleaning and standardizing feature values of the products
Author: GHonem
Author-email: <mahmoud.gh2016@gmail.com>
Keywords: python,dataquality
Classifier: Development Status :: 1 - Planning
Classifier: Intended Audience :: Developers
Classifier: Programming Language :: Python :: 3
Classifier: Operating System :: Unix
Classifier: Operating System :: MacOS :: MacOS X
Classifier: Operating System :: Microsoft :: Windows
Requires-Dist: colour
Requires-Dist: word2number
